ctlml_commons/__init__.py
ctlml_commons/entity/__init__.py
ctlml_commons/entity/aggregate_position.py
ctlml_commons/entity/auth_info.py
ctlml_commons/entity/bank_account.py
ctlml_commons/entity/buy_sell_request.py
ctlml_commons/entity/candle.py
ctlml_commons/entity/candle2.py
ctlml_commons/entity/cash_type.py
ctlml_commons/entity/chain.py
ctlml_commons/entity/config.py
ctlml_commons/entity/config_dir_type.py
ctlml_commons/entity/config_queue_type.py
ctlml_commons/entity/config_url_type.py
ctlml_commons/entity/direction.py
ctlml_commons/entity/dividend.py
ctlml_commons/entity/earnings.py
ctlml_commons/entity/effect.py
ctlml_commons/entity/execution.py
ctlml_commons/entity/execution_decision.py
ctlml_commons/entity/execution_request.py
ctlml_commons/entity/execution_type.py
ctlml_commons/entity/fundamentals.py
ctlml_commons/entity/historicals.py
ctlml_commons/entity/history.py
ctlml_commons/entity/investor.py
ctlml_commons/entity/investor_stats.py
ctlml_commons/entity/limit_buy_sell_request.py
ctlml_commons/entity/lot.py
ctlml_commons/entity/market.py
ctlml_commons/entity/mover.py
ctlml_commons/entity/news.py
ctlml_commons/entity/offer.py
ctlml_commons/entity/option.py
ctlml_commons/entity/option_type.py
ctlml_commons/entity/order.py
ctlml_commons/entity/popularity.py
ctlml_commons/entity/portfolio.py
ctlml_commons/entity/position.py
ctlml_commons/entity/price.py
ctlml_commons/entity/printable.py
ctlml_commons/entity/queue_message.py
ctlml_commons/entity/quote.py
ctlml_commons/entity/range_window.py
ctlml_commons/entity/ratings.py
ctlml_commons/entity/stat_type.py
ctlml_commons/entity/state.py
ctlml_commons/entity/status.py
ctlml_commons/entity/status_state.py
ctlml_commons/entity/stock.py
ctlml_commons/entity/strategy_decision.py
ctlml_commons/entity/tick.py
ctlml_commons/entity/time_in_force.py
ctlml_commons/entity/tradability.py
ctlml_commons/entity/transfer.py
ctlml_commons/entity/user.py
ctlml_commons/entity/crypto/__init__.py
ctlml_commons-0.0.36.dist-info/METADATA
ctlml_commons-0.0.36.dist-info/WHEEL
ctlml_commons-0.0.36.dist-info/top_level.txt
ctlml_commons-0.0.36.dist-info/RECORD
